{"cameraMode":{"drawMode":0,"name":"Shaded","section":"Shading Mode"},"sceneLighting":false,"audioPlay":false,"sceneViewState":{"showFog":true,"showMaterialUpdate":false,"showSkybox":false,"showFlares":true,"showImageEffects":true,"showParticleSystems":true},"in2DMode":false,"pivot":{"x":277.9590759277344,"y":22.11344337463379,"z":-0.6540336608886719},"rotation":{"x":0.058157652616500857,"y":0.006585889961570501,"z":0.0003768533933907747,"w":-0.9982955455780029},"size":34.66366195678711,"orthographic":false}