{"cameraMode":{"drawMode":0,"name":"Shaded","section":"Shading Mode"},"sceneLighting":false,"audioPlay":false,"sceneViewState":{"showFog":true,"showMaterialUpdate":false,"showSkybox":false,"showFlares":true,"showImageEffects":true,"showParticleSystems":true},"in2DMode":false,"pivot":{"x":52.79011917114258,"y":0.43346020579338076,"z":32.80401611328125},"rotation":{"x":-0.1273430585861206,"y":0.40161389112472536,"z":-0.056612081825733188,"w":-0.9051927924156189},"size":8.231647491455079,"orthographic":false}